splathash/__init__.py
splathash/apps.py
splathash/urls.py
splathash/views.py
splathash/data/__init__.py
splathash/data/input_data.py
splathash/data/node_response.py
splathash/data/output_data.py
splathash/engine/__init__.py
splathash/engine/application/__init__.py
splathash/engine/application/application.py
splathash/engine/context/__init__.py
splathash/engine/context/application_context.py
splathash/engine/converter/__init__.py
splathash/engine/converter/menu_output_converter.py
splathash/engine/converter/output_json_converter.py
splathash/engine/pagination/__init__.py
splathash/engine/pagination/context/__init__.py
splathash/engine/pagination/context/pagination_context.py
splathash/engine/pagination/pager/__init__.py
splathash/engine/pagination/pager/pager.py
splathash/engine/pagination/splitter/__init__.py
splathash/engine/pagination/splitter/message_splitter.py
splathash/engine/router/__init__.py
splathash/engine/router/router.py
splathash/node/__init__.py
splathash/node/node.py
splathash/response/__init__.py
splathash/response/response_handler.py
splathash/templates/splathash/index.html
tests/__init__.py
tests/settings.py
tests/urls.py
tests/wsgi.py
tests/splathash_tests/__init__.py
tests/splathash_tests/context/__init__.py
tests/splathash_tests/context/test_application_context.py
tests/splathash_tests/converter/__init__.py
tests/splathash_tests/converter/test_menu_output_converter.py
tests/splathash_tests/converter/test_output_json_converter.py
tests/splathash_tests/router/__init__.py
tests/splathash_tests/router/test_router.py
tests/test_app/__init__.py
tests/test_app/apps.py
tests/test_app/constants.py
tests/test_app/handlers.py
tests/test_app/routes.py
tests/test_app/screens.py
tests/test_app/views.py
splathash-1.0.0.dist-info/LICENSE
splathash-1.0.0.dist-info/METADATA
splathash-1.0.0.dist-info/WHEEL
splathash-1.0.0.dist-info/top_level.txt
splathash-1.0.0.dist-info/RECORD
